<?xml version="1.0" encoding="UTF-8"?>

<xwikidoc reference="Geo.192" locale="">
  <web>Geo</web>
  <name>192</name>
  <language/>
  <defaultLanguage/>
  <translation>0</translation>
  <parent>WebHome</parent>
  <creator>xwiki:XWiki.Admin</creator>
  <author>xwiki:XWiki.Admin</author>
  <customClass/>
  <contentAuthor>xwiki:XWiki.Admin</contentAuthor>
  <creationDate>1476655200000</creationDate>
  <date>1476655200000</date>
  <contentUpdateDate>1476655200000</contentUpdateDate>
  <version>1.1</version>
  <title>Cuba</title>
  <defaultTemplate/>
  <validationScript/>
  <comment/>
  <minorEdit>false</minorEdit>
  <syntaxId>xwiki/2.1</syntaxId>
  <hidden>false</hidden>
  <object>
    <class>
      <name>Geo.Code.CountryClass</name>
      <customClass/>
      <customMapping/>
      <defaultViewSheet/>
      <defaultEditSheet/>
      <defaultWeb/>
      <nameField/>
      <validationScript/>
      <name>
        <customDisplay>{{include document="AppWithinMinutes.Title" /}}</customDisplay>
        <disabled>0</disabled>
        <name>name</name>
        <number>1</number>
        <prettyName>name</prettyName>
        <script/>
        <unmodifiable>0</unmodifiable>
        <validationMessage/>
        <validationRegExp/>
        <classType>com.xpn.xwiki.objects.classes.ComputedFieldClass</classType>
      </name>
    </class>
    <name>Geo.192</name>
    <number>0</number>
    <className>Geo.Code.CountryClass</className>
    <guid>8778b34a-a6a0-48bb-b1ee-305907f445d2</guid>
  </object>
  <content/>
</xwikidoc>
